CHANGES.rst
DESCRIPTION.rst
LICENSE
MANIFEST.in
README.md
setup.py
resources/bolts.csv
resources/bolts_response.csv
resources/regression/wai/ma/algorithm/_CCAFilter/CCAFilter/default_setup/projection-X.csv
resources/regression/wai/ma/algorithm/_CCAFilter/CCAFilter/default_setup/projection-Y.csv
resources/regression/wai/ma/algorithm/_CCAFilter/CCAFilter/default_setup/transform.csv
resources/regression/wai/ma/algorithm/_CCAFilter/CCAFilter/lambda_X_10/projection-X.csv
resources/regression/wai/ma/algorithm/_CCAFilter/CCAFilter/lambda_X_10/projection-Y.csv
resources/regression/wai/ma/algorithm/_CCAFilter/CCAFilter/lambda_X_10/transform.csv
resources/regression/wai/ma/algorithm/_CCAFilter/CCAFilter/lambda_Y_10/projection-X.csv
resources/regression/wai/ma/algorithm/_CCAFilter/CCAFilter/lambda_Y_10/projection-Y.csv
resources/regression/wai/ma/algorithm/_CCAFilter/CCAFilter/lambda_Y_10/transform.csv
resources/regression/wai/ma/algorithm/_PCA/PCA/center/loadings.csv
resources/regression/wai/ma/algorithm/_PCA/PCA/center/scores.csv
resources/regression/wai/ma/algorithm/_PCA/PCA/center/transform.csv
resources/regression/wai/ma/algorithm/_PCA/PCA/default_setup/loadings.csv
resources/regression/wai/ma/algorithm/_PCA/PCA/default_setup/scores.csv
resources/regression/wai/ma/algorithm/_PCA/PCA/default_setup/transform.csv
resources/regression/wai/ma/algorithm/_PCA/PCA/max_cols_3/loadings.csv
resources/regression/wai/ma/algorithm/_PCA/PCA/max_cols_3/scores.csv
resources/regression/wai/ma/algorithm/_PCA/PCA/max_cols_3/transform.csv
resources/regression/wai/ma/algorithm/glsw/_EPO/EPO/alpha_1/projection.csv
resources/regression/wai/ma/algorithm/glsw/_EPO/EPO/alpha_1/transform.csv
resources/regression/wai/ma/algorithm/glsw/_EPO/EPO/alpha_100/projection.csv
resources/regression/wai/ma/algorithm/glsw/_EPO/EPO/alpha_100/transform.csv
resources/regression/wai/ma/algorithm/glsw/_EPO/EPO/default_setup/projection.csv
src/wai_ma.egg-info/PKG-INFO
src/wai_ma.egg-info/SOURCES.txt
src/wai_ma.egg-info/dependency_links.txt
src/wai_ma.egg-info/requires.txt
src/wai_ma.egg-info/top_level.txt
